contentmatcher/__init__.py
contentmatcher/classes.py
contentmatcher-0.0.1.dist-info/DESCRIPTION.rst
contentmatcher-0.0.1.dist-info/METADATA
contentmatcher-0.0.1.dist-info/RECORD
contentmatcher-0.0.1.dist-info/WHEEL
contentmatcher-0.0.1.dist-info/metadata.json
contentmatcher-0.0.1.dist-info/top_level.txt
tests/__init__.py
tests/test_matches.py
tests/test_speed.py
