Metadata-Version: 2.0
Name: contentmatcher
Version: 0.0.1
Summary: A pattern-based content matcher for Python
Home-page: https://github.com/brandonmpace/contentmatcher
Author: Brandon M. Pace
Author-email: brandonmpace@gmail.com
License: GNU Lesser General Public License v3 or later
Keywords: content pattern matcher
Platform: any
Classifier: Development Status :: 3 - Alpha
Classifier: License :: OSI Approved :: GNU Lesser General Public License v3 or later (LGPLv3+)
Classifier: Operating System :: OS Independent
Classifier: Programming Language :: Python :: 3
Requires-Python: >=3.6.5
